c_enum_generator/CGenHelperProvider.py
c_enum_generator/CGenSchemaProvider.py
c_enum_generator/__init__.py
c_enum_generator/resources/cenum.schema_v1.json
c_enum_generator/resources/templates/enum_h.j2
c_enum_generator/resources/templates/enum_string_functions_c.j2
c_enum_generator/resources/templates/enum_string_functions_h.j2
c_enum_generator/resources/templates/macros.j2
c_enum_generator/resources/templates/module_c.j2
c_enum_generator/resources/templates/module_h.j2
c_enum_generator/schema/CEnumsSchema.py
c_enum_generator/schema/__init__.py
c_enum_generator/schema/validate.py
c_enum_generator-0.1.4.dist-info/METADATA
c_enum_generator-0.1.4.dist-info/WHEEL
c_enum_generator-0.1.4.dist-info/entry_points.txt
c_enum_generator-0.1.4.dist-info/RECORD
