Metadata-Version: 2.4
Name: c-enum-generator
Version: 0.1.4
Summary: C enum generator
Author-email: Maciej Matuszak <maciej.matuszak@gmail.com>
License-Expression: MIT
Requires-Python: >=3.8
Requires-Dist: json2any>=0.1.3
